KS903_Natural_Voice_0003/__init__.py
KS903_Natural_Voice_0003/_init_.py
KS903NaturalIntonationAIVoice_vr_3-3.0.1.dist-info/METADATA
KS903NaturalIntonationAIVoice_vr_3-3.0.1.dist-info/WHEEL
KS903NaturalIntonationAIVoice_vr_3-3.0.1.dist-info/top_level.txt
KS903NaturalIntonationAIVoice_vr_3-3.0.1.dist-info/RECORD
